{
  "LEB": [{"@odata.etag":"","ItemInternalId":"8d35b0a6-9ab2-45b4-8f08-0b70a5a2487f","Ligne d'expression du besoin":"LEB-05170","Demandeur_x003a_ Nom complet":"Manuel PARIS","Lieu de livraison du besoin":"PL-AH_N01_Maintenance_Interne","Priorité":"Standard","Commentaires suivi":"PON342504293","Fournisseur":"SEFI","Livraison partielle souhaitée":"1","Date prévue de réception selon ARC":"46034","Date report de délai":"46128","Expression du besoin_x003a_ Expression du besoin":"46007.3451388889","Valideur_x003a_ Nom complet":"Manuel PARIS","Quantité":"1","N° de tracking":""},{"@odata.etag":"","ItemInternalId":"b80d2f48-ff2e-4820-a906-d41ff267a633","Ligne d'expression du besoin":"LEB-05171","Demandeur_x003a_ Nom complet":"Manuel PARIS","Lieu de livraison du besoin":"PL-AH_N01_Maintenance_Interne","Priorité":"Standard","Commentaires suivi":"PON342504293","Fournisseur":"SEFI","Livraison partielle souhaitée":"1","Date prévue de réception selon ARC":"46034","Date report de délai":"46128","Expression du besoin_x003a_ Expression du besoin":"46007.3451388889","Valideur_x003a_ Nom complet":"Manuel PARIS","Quantité":"1","N° de tracking":""},{"@odata.etag":"","ItemInternalId":"9003668b-9faa-4be2-a05e-4c972759ed21","Ligne d'expression du besoin":"LEB-05694","Demandeur_x003a_ Nom complet":"Pascal DODANE","Lieu de livraison du besoin":"PL-AH_Stock","Priorité":"Standard","Commentaires suivi":"PON342600908","Fournisseur":"SEFI","Livraison partielle souhaitée":"1","Date prévue de réception selon ARC":"46141","Date report de délai":"","Expression du besoin_x003a_ Expression du besoin":"46065.4034722222","Valideur_x003a_ Nom complet":"Manuel PARIS","Quantité":"1","N° de tracking":""},{"@odata.etag":"","ItemInternalId":"9f14f559-acba-491c-98a1-f8a408a4583a","Ligne d'expression du besoin":"LEB-05806","Demandeur_x003a_ Nom complet":"Marc BANTWELL","Lieu de livraison du besoin":"PL-AH_N01_Maintenance_Interne","Priorité":"Important","Commentaires suivi":"PON342601088","Fournisseur":"TECHMETA","Livraison partielle souhaitée":"0","Date prévue de réception selon ARC":"","Date report de délai":"","Expression du besoin_x003a_ Expression du besoin":"46078.5895833333","Valideur_x003a_ Nom complet":"Manuel PARIS","Quantité":"2","N° de tracking":""},{"@odata.etag":"","ItemInternalId":"4908dec7-43b5-40d7-895b-70db0da3ef5e","Ligne d'expression du besoin":"LEB-05895","Demandeur_x003a_ Nom complet":"David PIANELLI","Lieu de livraison du besoin":"PL-AH_M01_Atelier_ADF","Priorité":"Bloquant","Commentaires suivi":"PON342600947","Fournisseur":"YAMAZAKI","Livraison partielle souhaitée":"0","Date prévue de réception selon ARC":"46104","Date report de délai":"","Expression du besoin_x003a_ Expression du besoin":"46085.4423611111","Valideur_x003a_ Nom complet":"David PIANELLI","Quantité":"","N° de tracking":""},{"@odata.etag":"","ItemInternalId":"63f6649d-224f-4360-bf90-b5b08b8d12c8","Ligne d'expression du besoin":"LEB-06006","Demandeur_x003a_ Nom complet":"Clement MOINEREAU","Lieu de livraison du besoin":"PL-AH_N01_Maintenance_Interne","Priorité":"Important","Commentaires suivi":"PON342601087","Fournisseur":"ECOCLEAN","Livraison partielle souhaitée":"0","Date prévue de réception selon ARC":"","Date report de délai":"","Expression du besoin_x003a_ Expression du besoin":"46091.3333333333","Valideur_x003a_ Nom complet":"Manuel PARIS","Quantité":"2","N° de tracking":""},{"@odata.etag":"","ItemInternalId":"ed89ae99-9a59-4e4a-a2e4-4eaa7fde6738","Ligne d'expression du besoin":"LEB-06032","Demandeur_x003a_ Nom complet":"Romain SANTARNECCHI","Lieu de livraison du besoin":"PL-AH_Non_Applicable","Priorité":"Important","Commentaires suivi":"PON342601110","Fournisseur":"INTERPACK","Livraison partielle souhaitée":"0","Date prévue de réception selon ARC":"46099","Date report de délai":"","Expression du besoin_x003a_ Expression du besoin":"46092.4555555556","Valideur_x003a_ Nom complet":"Manuel PARIS","Quantité":"","N° de tracking":""},{"@odata.etag":"","ItemInternalId":"828fbc30-b9c0-49fe-adc1-0286c5b73967","Ligne d'expression du besoin":"LEB-06092","Demandeur_x003a_ Nom complet":"Christophe VAHRAMIAN","Lieu de livraison du besoin":"PL-AH_Stock","Priorité":"Standard","Commentaires suivi":"PON342601170","Fournisseur":"MCM","Livraison partielle souhaitée":"0","Date prévue de réception selon ARC":"46188","Date report de délai":"","Expression du besoin_x003a_ Expression du besoin":"46094.48125","Valideur_x003a_ Nom complet":"Manuel PARIS","Quantité":"1","N° de tracking":""},{"@odata.etag":"","ItemInternalId":"dd3628e0-b3a6-4e5e-8e03-90fcbe3b7d75","Ligne d'expression du besoin":"LEB-06096","Demandeur_x003a_ Nom complet":"Christophe CHABAUD","Lieu de livraison du besoin":"PL-AH_N01_Maintenance_Interne","Priorité":"Important","Commentaires suivi":"PON342601168","Fournisseur":"POMPE NPI","Livraison partielle souhaitée":"0","Date prévue de réception selon ARC":"46127","Date report de délai":"","Expression du besoin_x003a_ Expression du besoin":"46094.6722222222","Valideur_x003a_ Nom complet":"Manuel PARIS","Quantité":"1","N° de tracking":""},{"@odata.etag":"","ItemInternalId":"d3bda8d8-39f0-49c8-9c6f-405188c31ef5","Ligne d'expression du besoin":"LEB-06098","Demandeur_x003a_ Nom complet":"Christophe CHABAUD","Lieu de livraison du besoin":"PL-AH_N01_Maintenance_Interne","Priorité":"Important","Commentaires suivi":"PON342601165","Fournisseur":"BAMO","Livraison partielle souhaitée":"0","Date prévue de réception selon ARC":"","Date report de délai":"","Expression du besoin_x003a_ Expression du besoin":"46094.69375","Valideur_x003a_ Nom complet":"Manuel PARIS","Quantité":"","N° de tracking":""},{"@odata.etag":"","ItemInternalId":"2c2dc1fa-acdb-4a3c-b149-7432d88f0d00","Ligne d'expression du besoin":"LEB-06134","Demandeur_x003a_ Nom complet":"Christophe CHABAUD","Lieu de livraison du besoin":"PL-AH_N01_Maintenance_Interne","Priorité":"Important","Commentaires suivi":"PON342601559","Fournisseur":"MMPI","Livraison partielle souhaitée":"0","Date prévue de réception selon ARC":"","Date report de délai":"","Expression du besoin_x003a_ Expression du besoin":"46097.56875","Valideur_x003a_ Nom complet":"Manuel PARIS","Quantité":"1","N° de tracking":""},{"@odata.etag":"","ItemInternalId":"5583ead5-38d2-4cd8-8311-20311dbabdf3","Ligne d'expression du besoin":"LEB-06152","Demandeur_x003a_ Nom complet":"Alain CASTELIN","Lieu de livraison du besoin":"PL-AH_N01_Maintenance_Interne","Priorité":"Important","Commentaires suivi":"PON342601221","Fournisseur":"MAHR","Livraison partielle souhaitée":"1","Date prévue de réception selon ARC":"","Date report de délai":"","Expression du besoin_x003a_ Expression du besoin":"46097.8180555556","Valideur_x003a_ Nom complet":"Manuel PARIS","Quantité":"","N° de tracking":""},{"@odata.etag":"","ItemInternalId":"d824041b-354a-4798-b80e-a814eeda4a2f","Ligne d'expression du besoin":"LEB-06170","Demandeur_x003a_ Nom complet":"Christophe CHABAUD","Lieu de livraison du besoin":"PL-AH_N01_Maintenance_Interne","Priorité":"Important","Commentaires suivi":"PON342601308","Fournisseur":"AUTOMATEC","Livraison partielle souhaitée":"0","Date prévue de réception selon ARC":"46169","Date report de délai":"46174","Expression du besoin_x003a_ Expression du besoin":"46099.4034722222","Valideur_x003a_ Nom complet":"Manuel PARIS","Quantité":"1","N° de tracking":""},{"@odata.etag":"","ItemInternalId":"4c43aa83-5a0f-4ee7-8be7-dae8d259a673","Ligne d'expression du besoin":"LEB-06185","Demandeur_x003a_ Nom complet":"Clément SMAILI","Lieu de livraison du besoin":"PL-AH_N01_Maintenance_Interne","Priorité":"Standard","Commentaires suivi":"PON342601271","Fournisseur":"Atlantique Composant","Livraison partielle souhaitée":"1","Date prévue de réception selon ARC":"46141","Date report de délai":"46146","Expression du besoin_x003a_ Expression du besoin":"46100.3409722222","Valideur_x003a_ Nom complet":"Manuel PARIS","Quantité":"1","N° de tracking":""},{"@odata.etag":"","ItemInternalId":"75c4d4b0-1ab2-4147-aeb7-1148ecfed13b","Ligne d'expression du besoin":"LEB-06194","Demandeur_x003a_ Nom complet":"Alain CASTELIN","Lieu de livraison du besoin":"PL-AH_Stock","Priorité":"Important","Commentaires suivi":"PON342601292","Fournisseur":"SIEMENS","Livraison partielle souhaitée":"1","Date prévue de réception selon ARC":"46120","Date report de délai":"46133","Expression du besoin_x003a_ Expression du besoin":"46100.6395833333","Valideur_x003a_ Nom complet":"Manuel PARIS","Quantité":"1","N° de tracking":""},{"@odata.etag":"","ItemInternalId":"347b6358-c670-4544-be3b-ad6604bfdc36","Ligne d'expression du besoin":"LEB-06212","Demandeur_x003a_ Nom complet":"Manuel PARIS","Lieu de livraison du besoin":"PL-AH_N01_Maintenance_Interne","Priorité":"Bloquant","Commentaires suivi":"PON342601270","Fournisseur":"KAPP-NILES","Livraison partielle souhaitée":"0","Date prévue de réception selon ARC":"46105","Date report de délai":"46111","Expression du besoin_x003a_ Expression du besoin":"46100.6958333333","Valideur_x003a_ Nom complet":"Manuel PARIS","Quantité":"6","N° de tracking":"https://www.tnt.com/track?cons=WW371278966NBE202603241219&searchType=CON&source=share"},{"@odata.etag":"","ItemInternalId":"6865014e-34fa-4a47-9d75-cc46d81595db","Ligne d'expression du besoin":"LEB-06211","Demandeur_x003a_ Nom complet":"Manuel PARIS","Lieu de livraison du besoin":"PL-AH_N01_Maintenance_Interne","Priorité":"Bloquant","Commentaires suivi":"PON342601270","Fournisseur":"KAPP-NILES","Livraison partielle souhaitée":"0","Date prévue de réception selon ARC":"46105","Date report de délai":"46111","Expression du besoin_x003a_ Expression du besoin":"46100.6958333333","Valideur_x003a_ Nom complet":"Manuel PARIS","Quantité":"1","N° de tracking":"https://www.tnt.com/express/fr_fr/site/outils-expedition/suivi.html?searchType=con&cons=371278966"},{"@odata.etag":"","ItemInternalId":"da360db2-d003-4e45-904d-020f29451754","Ligne d'expression du besoin":"LEB-06225","Demandeur_x003a_ Nom complet":"Christophe VAHRAMIAN","Lieu de livraison du besoin":"PL-AH_N01_Maintenance_Interne","Priorité":"Important","Commentaires suivi":"PON342601586","Fournisseur":"LEKAP VERRE","Livraison partielle souhaitée":"0","Date prévue de réception selon ARC":"","Date report de délai":"","Expression du besoin_x003a_ Expression du besoin":"46101.7145833333","Valideur_x003a_ Nom complet":"Manuel PARIS","Quantité":"2","N° de tracking":""},{"@odata.etag":"","ItemInternalId":"7ff83913-1823-4b4a-8c18-5ed72ea16743","Ligne d'expression du besoin":"LEB-06230","Demandeur_x003a_ Nom complet":"Frederic SERRIER","Lieu de livraison du besoin":"PL-AH_N01_Maintenance_Interne","Priorité":"Standard","Commentaires suivi":"PON342601491","Fournisseur":"REXEL","Livraison partielle souhaitée":"0","Date prévue de réception selon ARC":"46133","Date report de délai":"","Expression du besoin_x003a_ Expression du besoin":"46104.525","Valideur_x003a_ Nom complet":"Manuel PARIS","Quantité":"2","N° de tracking":""},{"@odata.etag":"","ItemInternalId":"1c2a687f-585d-4c20-b000-bd4ba5245797","Ligne d'expression du besoin":"LEB-06260","Demandeur_x003a_ Nom complet":"Clément SMAILI","Lieu de livraison du besoin":"PL-AH_N01_Maintenance_Interne","Priorité":"Important","Commentaires suivi":"PON342601524","Fournisseur":"MICHAUD CHAILLY","Livraison partielle souhaitée":"0","Date prévue de réception selon ARC":"46121","Date report de délai":"","Expression du besoin_x003a_ Expression du besoin":"46105.6541666667","Valideur_x003a_ Nom complet":"Manuel PARIS","Quantité":"1","N° de tracking":""},{"@odata.etag":"","ItemInternalId":"cb7ef7c6-263f-4833-9f5a-afec507c36ca","Ligne d'expression du besoin":"LEB-06271","Demandeur_x003a_ Nom complet":"Anthony TASHJIAN","Lieu de livraison du besoin":"PL-AH_N01_Maintenance_Interne","Priorité":"Standard","Commentaires suivi":"PON342601344","Fournisseur":"RADIOSPARES","Livraison partielle souhaitée":"0","Date prévue de réception selon ARC":"46155","Date report de délai":"46160","Expression du besoin_x003a_ Expression du besoin":"46105.8243055556","Valideur_x003a_ Nom complet":"Manuel PARIS","Quantité":"3","N° de tracking":""},{"@odata.etag":"","ItemInternalId":"f5763f46-22a3-4073-8f56-11e91db79c07","Ligne d'expression du besoin":"LEB-06395","Demandeur_x003a_ Nom complet":"Nicolas DI-ROLLO","Lieu de livraison du besoin":"PL-AH_N01_Maintenance_Interne","Priorité":"Important","Commentaires suivi":"PON342600869","Fournisseur":"UPS","Livraison partielle souhaitée":"0","Date prévue de réception selon ARC":"","Date report de délai":"","Expression du besoin_x003a_ Expression du besoin":"46106.0701388889","Valideur_x003a_ Nom complet":"Manuel PARIS","Quantité":"","N° de tracking":"UPS 1Z2A835W6628340948"},{"@odata.etag":"","ItemInternalId":"9f014754-c389-4c0b-a4a2-40ed50a56586","Ligne d'expression du besoin":"LEB-06383","Demandeur_x003a_ Nom complet":"Frederic SERRIER","Lieu de livraison du besoin":"PL-AH_N01_Maintenance_Interne","Priorité":"Standard","Commentaires suivi":"PON342601510","Fournisseur":"DEPPCO","Livraison partielle souhaitée":"0","Date prévue de réception selon ARC":"46128","Date report de délai":"","Expression du besoin_x003a_ Expression du besoin":"46112.5784722222","Valideur_x003a_ Nom complet":"Manuel PARIS","Quantité":"1","N° de tracking":""},{"@odata.etag":"","ItemInternalId":"b0c49297-5cce-4ef7-b3af-8521389c5f14","Ligne d'expression du besoin":"LEB-06382","Demandeur_x003a_ Nom complet":"Nicolas MAGRO","Lieu de livraison du besoin":"PL-AH_N01_Maintenance_Interne","Priorité":"Standard","Commentaires suivi":"","Fournisseur":"MANUTAN","Livraison partielle souhaitée":"0","Date prévue de réception selon ARC":"","Date report de délai":"","Expression du besoin_x003a_ Expression du besoin":"46112.5659722222","Valideur_x003a_ Nom complet":"Manuel PARIS","Quantité":"2","N° de tracking":""},{"@odata.etag":"","ItemInternalId":"3f23396e-70df-4fb6-9922-080e63a83f35","Ligne d'expression du besoin":"LEB-06387","Demandeur_x003a_ Nom complet":"Sébastien TRIPIER","Lieu de livraison du besoin":"PL-AH_Stock","Priorité":"Important","Commentaires suivi":"PON342601519","Fournisseur":"HOUGHTON","Livraison partielle souhaitée":"0","Date prévue de réception selon ARC":"46127","Date report de délai":"46132","Expression du besoin_x003a_ Expression du besoin":"46112.7152777778","Valideur_x003a_ Nom complet":"Sébastien TRIPIER","Quantité":"1000","N° de tracking":""},{"@odata.etag":"","ItemInternalId":"ceebbdb2-a017-441f-84e3-21c159fd6f3a","Ligne d'expression du besoin":"LEB-06391","Demandeur_x003a_ Nom complet":"Manuel PARIS","Lieu de livraison du besoin":"PL-AH_N01_Maintenance_Interne","Priorité":"Standard","Commentaires suivi":"PON342601522","Fournisseur":"SICK","Livraison partielle souhaitée":"0","Date prévue de réception selon ARC":"46132","Date report de délai":"46139","Expression du besoin_x003a_ Expression du besoin":"46112.7784722222","Valideur_x003a_ Nom complet":"Manuel PARIS","Quantité":"1","N° de tracking":""},{"@odata.etag":"","ItemInternalId":"2ab452b8-ee4a-43ad-a698-aedb7ef06d95","Ligne d'expression du besoin":"LEB-06388","Demandeur_x003a_ Nom complet":"Arnaud TIERCET","Lieu de livraison du besoin":"PL-AH_N01_Maintenance_Interne","Priorité":"Standard","Commentaires suivi":"PON342601564","Fournisseur":"Atlantique Composant","Livraison partielle souhaitée":"0","Date prévue de réception selon ARC":"","Date report de délai":"","Expression du besoin_x003a_ Expression du besoin":"46112.7402777778","Valideur_x003a_ Nom complet":"Manuel PARIS","Quantité":"1","N° de tracking":""},{"@odata.etag":"","ItemInternalId":"e7128017-cce2-4391-a26e-b99ff2ac414a","Ligne d'expression du besoin":"LEB-06389","Demandeur_x003a_ Nom complet":"Arnaud TIERCET","Lieu de livraison du besoin":"PL-AH_N01_Maintenance_Interne","Priorité":"Standard","Commentaires suivi":"PON342601564","Fournisseur":"Atlantique Composant","Livraison partielle souhaitée":"0","Date prévue de réception selon ARC":"","Date report de délai":"","Expression du besoin_x003a_ Expression du besoin":"46112.7402777778","Valideur_x003a_ Nom complet":"Manuel PARIS","Quantité":"1","N° de tracking":""},{"@odata.etag":"","ItemInternalId":"25522fd9-4e84-46aa-b67f-bc045b7eedba","Ligne d'expression du besoin":"LEB-06401","Demandeur_x003a_ Nom complet":"Guillaume FACCIOTTI","Lieu de livraison du besoin":"PL-AH_N01_Maintenance_Interne","Priorité":"Standard","Commentaires suivi":"PON342601549","Fournisseur":"SETIN","Livraison partielle souhaitée":"0","Date prévue de réception selon ARC":"46132","Date report de délai":"","Expression du besoin_x003a_ Expression du besoin":"46114.2770833333","Valideur_x003a_ Nom complet":"Manuel PARIS","Quantité":"2","N° de tracking":""},{"@odata.etag":"","ItemInternalId":"7431ac3b-eb4d-4a5b-9bb6-01427265e318","Ligne d'expression du besoin":"LEB-06430","Demandeur_x003a_ Nom complet":"Manuel PARIS","Lieu de livraison du besoin":"PL-AH_N01_Maintenance_Interne","Priorité":"Standard","Commentaires suivi":"PON342601580","Fournisseur":"DMG MORI","Livraison partielle souhaitée":"0","Date prévue de réception selon ARC":"46135","Date report de délai":"","Expression du besoin_x003a_ Expression du besoin":"46119.5006944444","Valideur_x003a_ Nom complet":"Manuel PARIS","Quantité":"3","N° de tracking":""},{"@odata.etag":"","ItemInternalId":"b6c14af4-0b50-4e03-b6ff-fdc8f086ef05","Ligne d'expression du besoin":"LEB-06431","Demandeur_x003a_ Nom complet":"Anthony TASHJIAN","Lieu de livraison du besoin":"PL-AH_N01_Maintenance_Interne","Priorité":"Bloquant","Commentaires suivi":"PON342601572","Fournisseur":"KAPP-NILES","Livraison partielle souhaitée":"0","Date prévue de réception selon ARC":"46125","Date report de délai":"46132","Expression du besoin_x003a_ Expression du besoin":"46119.5840277778","Valideur_x003a_ Nom complet":"Manuel PARIS","Quantité":"1","N° de tracking":""},{"@odata.etag":"","ItemInternalId":"a53aa35f-7c7f-411f-a9da-a1b7245cb9cb","Ligne d'expression du besoin":"LEB-06436","Demandeur_x003a_ Nom complet":"Henri ROSSI","Lieu de livraison du besoin":"PL-AH_N01_Maintenance_Interne","Priorité":"Important","Commentaires suivi":"PON342601575","Fournisseur":"REXEL","Livraison partielle souhaitée":"0","Date prévue de réception selon ARC":"46139","Date report de délai":"46141","Expression du besoin_x003a_ Expression du besoin":"46119.7944444444","Valideur_x003a_ Nom complet":"Manuel PARIS","Quantité":"1","N° de tracking":""},{"@odata.etag":"","ItemInternalId":"9f5c8dce-98d9-45e6-9552-12a436986136","Ligne d'expression du besoin":"LEB-06437","Demandeur_x003a_ Nom complet":"Henri ROSSI","Lieu de livraison du besoin":"PL-AH_N01_Maintenance_Interne","Priorité":"Important","Commentaires suivi":"PON342601582","Fournisseur":"REXEL","Livraison partielle souhaitée":"0","Date prévue de réception selon ARC":"46136","Date report de délai":"","Expression du besoin_x003a_ Expression du besoin":"46119.7944444444","Valideur_x003a_ Nom complet":"Manuel PARIS","Quantité":"1","N° de tracking":""},{"@odata.etag":"","ItemInternalId":"5e7062a5-3ca9-4da2-8fcc-58fd352ee372","Ligne d'expression du besoin":"LEB-06459","Demandeur_x003a_ Nom complet":"Nicolas DI-ROLLO","Lieu de livraison du besoin":"PL-AH_N01_Maintenance_Interne","Priorité":"Bloquant","Commentaires suivi":"PON342601567","Fournisseur":"ASERTI","Livraison partielle souhaitée":"0","Date prévue de réception selon ARC":"46132","Date report de délai":"","Expression du besoin_x003a_ Expression du besoin":"46120.4479166667","Valideur_x003a_ Nom complet":"Manuel PARIS","Quantité":"1","N° de tracking":""},{"@odata.etag":"","ItemInternalId":"bbf553c4-8e63-4c35-b38a-839aaef4ed22","Ligne d'expression du besoin":"LEB-06463","Demandeur_x003a_ Nom complet":"Clément SMAILI","Lieu de livraison du besoin":"PL-AH_N01_Maintenance_Interne","Priorité":"Standard","Commentaires suivi":"PON342601593","Fournisseur":"SONEPAR","Livraison partielle souhaitée":"0","Date prévue de réception selon ARC":"46136","Date report de délai":"","Expression du besoin_x003a_ Expression du besoin":"46120.6680555556","Valideur_x003a_ Nom complet":"Manuel PARIS","Quantité":"12","N° de tracking":""},{"@odata.etag":"","ItemInternalId":"8b0ccb58-8c3c-44ce-a7d8-834521530486","Ligne d'expression du besoin":"LEB-06473","Demandeur_x003a_ Nom complet":"Julien ROUSSILLOUX","Lieu de livraison du besoin":"PL-AH_N01_Maintenance_Interne","Priorité":"Bloquant","Commentaires suivi":"PON342601585","Fournisseur":"RMS","Livraison partielle souhaitée":"0","Date prévue de réception selon ARC":"","Date report de délai":"","Expression du besoin_x003a_ Expression du besoin":"46121.6569444444","Valideur_x003a_ Nom complet":"Manuel PARIS","Quantité":"1","N° de tracking":""},{"@odata.etag":"","ItemInternalId":"b1c515f5-4ecd-495a-9ca7-2e2cf45aa336","Ligne d'expression du besoin":"","Demandeur_x003a_ Nom complet":"","Lieu de livraison du besoin":"","Priorité":"","Commentaires suivi":"","Fournisseur":"","Livraison partielle souhaitée":"","Date prévue de réception selon ARC":"","Date report de délai":"","Expression du besoin_x003a_ Expression du besoin":"","Valideur_x003a_ Nom complet":"","Quantité":"","N° de tracking":""},{"@odata.etag":"","ItemInternalId":"e9ad4ed2-a136-493a-a7b8-993cff1c8a23","Ligne d'expression du besoin":"","Demandeur_x003a_ Nom complet":"","Lieu de livraison du besoin":"","Priorité":"","Commentaires suivi":"","Fournisseur":"","Livraison partielle souhaitée":"","Date prévue de réception selon ARC":"","Date report de délai":"","Expression du besoin_x003a_ Expression du besoin":"","Valideur_x003a_ Nom complet":"","Quantité":"","N° de tracking":""}]
}